LICENSE
README.md
setup.py
virtue/__init__.py
virtue/__main__.py
virtue/core.py
virtue_git.egg-info/PKG-INFO
virtue_git.egg-info/SOURCES.txt
virtue_git.egg-info/dependency_links.txt
virtue_git.egg-info/entry_points.txt
virtue_git.egg-info/requires.txt
virtue_git.egg-info/top_level.txt