Metadata-Version: 2.1
Name: virtue-git
Version: 1.3.3
Summary: Gather information about a GitHub account
Home-page: https://github.com/drooling/virtue
Author: Surtains
Author-email: surtains@riseup.net
License: GNU General Public License v3 (GPLv3)
Project-URL: Source, https://github.com/drooling/virtue
Platform: UNKNOWN
Classifier: Programming Language :: Python :: 3.9
License-File: LICENSE
